django_admin_jqueryui_tabs/__init__.py
django_admin_jqueryui_tabs/mixins.py
django_admin_jqueryui_tabs/static/css/tabs.css
django_admin_jqueryui_tabs/static/jquery-ui-1.12.1/jquery-ui.css
django_admin_jqueryui_tabs/static/jquery-ui-1.12.1/jquery-ui.js
django_admin_jqueryui_tabs/static/jquery-ui-1.12.1/jquery-ui.min.css
django_admin_jqueryui_tabs/static/jquery-ui-1.12.1/jquery-ui.min.js
django_admin_jqueryui_tabs/static/jquery-ui-1.12.1/jquery-ui.structure.css
django_admin_jqueryui_tabs/static/jquery-ui-1.12.1/jquery-ui.structure.min.css
django_admin_jqueryui_tabs/static/jquery-ui-1.12.1/jquery-ui.theme.css
django_admin_jqueryui_tabs/static/jquery-ui-1.12.1/jquery-ui.theme.min.css
django_admin_jqueryui_tabs/static/jquery-ui-1.12.1/themes/smoothness/jquery-ui.css
django_admin_jqueryui_tabs/templates/admin/jqueryui_tabs/change_form.html
django_admin_jqueryui_tabs/templates/admin/jqueryui_tabs/edit_inline/stacked.html
django_admin_jqueryui_tabs/templates/admin/jqueryui_tabs/edit_inline/tabular.html
django_admin_jqueryui_tabs/templates/admin/jqueryui_tabs/includes/fieldset.html
django_admin_jqueryui_tabs-0.1.1.dist-info/METADATA
django_admin_jqueryui_tabs-0.1.1.dist-info/WHEEL
django_admin_jqueryui_tabs-0.1.1.dist-info/top_level.txt
django_admin_jqueryui_tabs-0.1.1.dist-info/RECORD
